# workModule(argc=1) varnames=('mody', 'PlayerMessages', 'new_PlayerMessages_init', 'new_startVisual', 'new_stopVisual', 'new_targetFocus', 'new_targetBlur', 'new_doHighlightOperation', 'getIsSquad', 'getIsPlayer', 'getIsFriendly', 'getIsVisibleLiveEnemy', 'new__startBattle', 'new__stopBattle', 'new_PlayerHandleKey_init')
   0 LOAD_CONST             -1
   3 LOAD_CONST             ('methodcaller',)
   6 IMPORT_NAME            operator
   9 IMPORT_FROM            methodcaller
  12 STORE_DEREF            methodcaller
  15 POP_TOP
  16 LOAD_CONST             -1
  19 LOAD_CONST             ('PlayerMessages',)
  22 IMPORT_NAME            gui.Scaleform.daapi.view.battle.shared.messages.player_messages
  25 IMPORT_FROM            PlayerMessages
  28 STORE_FAST             PlayerMessages
  31 POP_TOP
  32 LOAD_FAST              PlayerMessages
  35 LOAD_ATTR              __init__
  38 STORE_DEREF            old_PlayerMessages_init
  41 LOAD_CLOSURE           PlayerAvatar
  44 LOAD_CLOSURE           old_PlayerMessages_init
  47 BUILD_TUPLE            2
  50 LOAD_CONST             <code new_PlayerMessages_init>
  53 MAKE_CLOSURE           0
  56 STORE_FAST             new_PlayerMessages_init
  59 LOAD_FAST              new_PlayerMessages_init
  62 LOAD_FAST              PlayerMessages
  65 STORE_ATTR             __init__
  68 LOAD_CLOSURE           Vehicle
  71 LOAD_CLOSURE           mody
  74 LOAD_CLOSURE           removeEdge
  77 BUILD_TUPLE            3
  80 LOAD_CONST             <code addEdge>
  83 MAKE_CLOSURE           0
  86 STORE_DEREF            addEdge
  89 LOAD_GLOBAL            True
  92 LOAD_CLOSURE           Vehicle
  95 BUILD_TUPLE            1
  98 LOAD_CONST             <code removeEdge>
 101 MAKE_CLOSURE           1
 104 STORE_DEREF            removeEdge
 107 LOAD_CLOSURE           DrawControl
 110 LOAD_CLOSURE           GetObstacle
 113 LOAD_CLOSURE           GetVehicleViewAngle
 116 LOAD_CLOSURE           Vehicle
 119 LOAD_CLOSURE           addEdge
 122 LOAD_CLOSURE           mody
 125 LOAD_CLOSURE           removeEdge
 128 BUILD_TUPLE            7
 131 LOAD_CONST             <code DrawControl>
 134 MAKE_CLOSURE           0
 137 STORE_DEREF            DrawControl
 140 LOAD_CLOSURE           removeEdge
 143 BUILD_TUPLE            1
 146 LOAD_CONST             <code onVehicleKilled>
 149 MAKE_CLOSURE           0
 152 STORE_DEREF            onVehicleKilled
 155 LOAD_DEREF             Vehicle
 158 LOAD_ATTR              startVisual
 161 LOAD_CONST             <code new_startVisual>
 164 MAKE_FUNCTION          1
 167 STORE_FAST             new_startVisual
 170 LOAD_DEREF             PlayerAvatar
 173 LOAD_ATTR              vehicle_onLeaveWorld
 176 LOAD_CLOSURE           removeEdge
 179 BUILD_TUPLE            1
 182 LOAD_CONST             <code new_stopVisual>
 185 MAKE_CLOSURE           1
 188 STORE_FAST             new_stopVisual
 191 LOAD_FAST              new_startVisual
 194 LOAD_DEREF             Vehicle
 197 STORE_ATTR             startVisual
 200 LOAD_FAST              new_stopVisual
 203 LOAD_DEREF             PlayerAvatar
 206 STORE_ATTR             vehicle_onLeaveWorld
 209 LOAD_DEREF             PlayerAvatar
 212 LOAD_ATTR              targetFocus
 215 LOAD_CLOSURE           Vehicle
 218 LOAD_CLOSURE           mody
 221 LOAD_CLOSURE           removeEdge
 224 BUILD_TUPLE            3
 227 LOAD_CONST             <code new_targetFocus>
 230 MAKE_CLOSURE           1
 233 STORE_FAST             new_targetFocus
 236 LOAD_DEREF             PlayerAvatar
 239 LOAD_ATTR              targetBlur
 242 LOAD_CLOSURE           Vehicle
 245 LOAD_CLOSURE           mody
 248 BUILD_TUPLE            2
 251 LOAD_CONST             <code new_targetBlur>
 254 MAKE_CLOSURE           1
 257 STORE_FAST             new_targetBlur
 260 LOAD_FAST              new_targetFocus
 263 LOAD_DEREF             PlayerAvatar
 266 STORE_ATTR             targetFocus
 269 LOAD_FAST              new_targetBlur
 272 LOAD_DEREF             PlayerAvatar
 275 STORE_ATTR             targetBlur
 278 LOAD_GLOBAL            IS_LESTA
 281 POP_JUMP_IF_FALSE      to 627
 284 LOAD_CLOSURE           mody
 287 LOAD_CLOSURE           old_doHighlightOperation
 290 BUILD_TUPLE            2
 293 LOAD_CONST             <code new_doHighlightOperation>
 296 MAKE_CLOSURE           0
 299 STORE_FAST             new_doHighlightOperation
 302 LOAD_DEREF             Highlighter
 305 LOAD_ATTR              _Highlighter__doHighlightOperation
 308 STORE_DEREF            old_doHighlightOperation
 311 LOAD_FAST              new_doHighlightOperation
 314 LOAD_DEREF             Highlighter
 317 STORE_ATTR             _Highlighter__doHighlightOperation
 320 LOAD_GLOBAL            True
 323 LOAD_CLOSURE           cameras
 326 BUILD_TUPLE            1
 329 LOAD_CONST             <code GetVehicleViewAngle>
 332 MAKE_CLOSURE           1
 335 STORE_DEREF            GetVehicleViewAngle
 338 LOAD_GLOBAL            True
 341 LOAD_CLOSURE           collideDynamicAndStatic
 344 BUILD_TUPLE            1
 347 LOAD_CONST             <code GetObstacle>
 350 MAKE_CLOSURE           1
 353 STORE_DEREF            GetObstacle
 356 LOAD_CONST             <code getBattleOn>
 359 MAKE_FUNCTION          0
 362 STORE_DEREF            getBattleOn
 365 LOAD_CLOSURE           getBattleOn
 368 BUILD_TUPLE            1
 371 LOAD_CONST             <code getIsSquad>
 374 MAKE_CLOSURE           0
 377 STORE_FAST             getIsSquad
 380 LOAD_CLOSURE           getBattleOn
 383 BUILD_TUPLE            1
 386 LOAD_CONST             <code getIsPlayer>
 389 MAKE_CLOSURE           0
 392 STORE_FAST             getIsPlayer
 395 LOAD_CLOSURE           getBattleOn
 398 BUILD_TUPLE            1
 401 LOAD_CONST             <code getIsLive>
 404 MAKE_CLOSURE           0
 407 STORE_DEREF            getIsLive
 410 LOAD_CLOSURE           getBattleOn
 413 BUILD_TUPLE            1
 416 LOAD_CONST             <code getIsFriendly>
 419 MAKE_CLOSURE           0
 422 STORE_FAST             getIsFriendly
 425 LOAD_CLOSURE           getBattleOn
 428 BUILD_TUPLE            1
 431 LOAD_CONST             <code getIsVisible>
 434 MAKE_CLOSURE           0
 437 STORE_DEREF            getIsVisible
 440 LOAD_CLOSURE           getIsLive
 443 LOAD_CLOSURE           getIsVisible
 446 BUILD_TUPLE            2
 449 LOAD_CONST             <code getIsVisibleLiveEnemy>
 452 MAKE_CLOSURE           0
 455 STORE_FAST             getIsVisibleLiveEnemy
 458 LOAD_CLOSURE           LoadConfLoop
 461 LOAD_CLOSURE           PlayerAvatar
 464 LOAD_CLOSURE           methodcaller
 467 LOAD_CLOSURE           mody
 470 BUILD_TUPLE            4
 473 LOAD_CONST             <code LoadConfLoop>
 476 MAKE_CLOSURE           0
 479 STORE_DEREF            LoadConfLoop
 482 LOAD_CLOSURE           DrawControl
 485 LOAD_CLOSURE           LoadConfLoop
 488 LOAD_CLOSURE           getResolut
 491 LOAD_CLOSURE           mody
 494 LOAD_CLOSURE           old__startBattle
 497 LOAD_CLOSURE           onVehicleKilled
 500 BUILD_TUPLE            6
 503 LOAD_CONST             <code new__startBattle>
 506 MAKE_CLOSURE           0
 509 STORE_FAST             new__startBattle
 512 LOAD_DEREF             PlayerAvatar
 515 LOAD_ATTR              _PlayerAvatar__startGUI
 518 STORE_DEREF            old__startBattle
 521 LOAD_FAST              new__startBattle
 524 LOAD_DEREF             PlayerAvatar
 527 STORE_ATTR             _PlayerAvatar__startGUI
 530 LOAD_CLOSURE           mody
 533 LOAD_CLOSURE           old__stopBattle
 536 LOAD_CLOSURE           onVehicleKilled
 539 BUILD_TUPLE            3
 542 LOAD_CONST             <code new__stopBattle>
 545 MAKE_CLOSURE           0
 548 STORE_FAST             new__stopBattle
 551 LOAD_DEREF             PlayerAvatar
 554 LOAD_ATTR              _PlayerAvatar__destroyGUI
 557 STORE_DEREF            old__stopBattle
 560 LOAD_FAST              new__stopBattle
 563 LOAD_DEREF             PlayerAvatar
 566 STORE_ATTR             _PlayerAvatar__destroyGUI
 569 LOAD_CLOSURE           DrawControl
 572 LOAD_CLOSURE           Keys
 575 LOAD_CLOSURE           LoadConfLoop
 578 LOAD_CLOSURE           PlayerAvatar
 581 LOAD_CLOSURE           getResolut
 584 LOAD_CLOSURE           methodcaller
 587 LOAD_CLOSURE           mody
 590 LOAD_CLOSURE           pre_PlayerHandleKey_init
 593 BUILD_TUPLE            8
 596 LOAD_CONST             <code new_PlayerHandleKey_init>
 599 MAKE_CLOSURE           0
 602 STORE_FAST             new_PlayerHandleKey_init
 605 LOAD_DEREF             PlayerAvatar
 608 LOAD_ATTR              handleKey
 611 STORE_DEREF            pre_PlayerHandleKey_init
 614 LOAD_FAST              new_PlayerHandleKey_init
 617 LOAD_DEREF             PlayerAvatar
 620 STORE_ATTR             handleKey
 623 LOAD_CONST             None
 626 RETURN_VALUE
 627 LOAD_CLOSURE           mody
 630 LOAD_CLOSURE           old_doHighlightOperation
 633 BUILD_TUPLE            2
 636 LOAD_CONST             <code new_doHighlightOperation>
 639 MAKE_CLOSURE           0
 642 STORE_FAST             new_doHighlightOperation
 645 JUMP_ABSOLUTE          to 302

  # new_PlayerMessages_init(argc=1) varnames=('self',)
     0 LOAD_DEREF             old_PlayerMessages_init
     3 LOAD_FAST              self
     6 CALL_FUNCTION          1
     9 POP_TOP
    10 LOAD_FAST              self
    13 LOAD_DEREF             PlayerAvatar
    16 STORE_ATTR             selfMsg
    19 LOAD_CONST             None
    22 RETURN_VALUE

  # addEdge(argc=1) varnames=('vehicle',)
     0 LOAD_DEREF             mody
     3 LOAD_ATTR              modEnable
     6 POP_JUMP_IF_FALSE      to 68
     9 LOAD_GLOBAL            isinstance
    12 LOAD_FAST              vehicle
    15 LOAD_DEREF             Vehicle
    18 CALL_FUNCTION          2
    21 POP_JUMP_IF_FALSE      to 68
    24 LOAD_FAST              vehicle
    27 LOAD_ATTR              isStarted
    30 POP_JUMP_IF_FALSE      to 68
    33 LOAD_FAST              vehicle
    36 LOAD_ATTR              isAlive
    39 CALL_FUNCTION          0
    42 POP_JUMP_IF_FALSE      to 68
    45 LOAD_DEREF             removeEdge
    48 LOAD_FAST              vehicle
    51 LOAD_GLOBAL            False
    54 CALL_FUNCTION          2
    57 POP_TOP
    58 LOAD_FAST              vehicle
    61 LOAD_ATTR              drawEdge
    64 CALL_FUNCTION          0
    67 POP_TOP
    68 LOAD_CONST             None
    71 RETURN_VALUE

  # removeEdge(argc=2) varnames=('vehicle', 'force')
     0 LOAD_GLOBAL            isinstance
     3 LOAD_FAST              vehicle
     6 LOAD_DEREF             Vehicle
     9 CALL_FUNCTION          2
    12 POP_JUMP_IF_FALSE      to 80
    15 LOAD_FAST              vehicle
    18 LOAD_ATTR              isStarted
    21 POP_JUMP_IF_FALSE      to 80
    24 LOAD_FAST              vehicle
    27 LOAD_ATTR              isAlive
    30 CALL_FUNCTION          0
    33 UNARY_NOT
    34 POP_JUMP_IF_TRUE       to 55
    37 LOAD_GLOBAL            BigWorld
    40 LOAD_ATTR              target
    43 CALL_FUNCTION          0
    46 LOAD_FAST              vehicle
    49 COMPARE_OP             3
    52 POP_JUMP_IF_FALSE      to 70
    55 LOAD_FAST              force
    58 POP_JUMP_IF_FALSE      to 70
    61 LOAD_CONST             None
    64 LOAD_FAST              vehicle
    67 STORE_ATTR             zj_adgclr
    70 LOAD_FAST              vehicle
    73 LOAD_ATTR              removeEdge
    76 CALL_FUNCTION          0
    79 POP_TOP
    80 LOAD_CONST             None
    83 RETURN_VALUE

  # DrawControl(argc=0) varnames=('vehicle', 'fam', 'adgclr', 't_clr', 'distance')
     0 LOAD_DEREF             mody
     3 LOAD_ATTR              modEnable
     6 POP_JUMP_IF_TRUE       to 73
     9 SETUP_LOOP             to 69
    12 LOAD_GLOBAL            BigWorld
    15 LOAD_ATTR              entities
    18 LOAD_ATTR              values
    21 CALL_FUNCTION          0
    24 GET_ITER
    25 FOR_ITER               to 68
    28 STORE_FAST             vehicle
    31 LOAD_GLOBAL            isinstance
    34 LOAD_FAST              vehicle
    37 LOAD_DEREF             Vehicle
    40 CALL_FUNCTION          2
    43 POP_JUMP_IF_FALSE      to 25
    46 LOAD_FAST              vehicle
    49 LOAD_ATTR              isStarted
    52 POP_JUMP_IF_FALSE      to 25
    55 LOAD_DEREF             removeEdge
    58 LOAD_FAST              vehicle
    61 CALL_FUNCTION          1
    64 POP_TOP
    65 JUMP_ABSOLUTE          to 25
    68 POP_BLOCK
    69 LOAD_CONST             None
    72 RETURN_VALUE
    73 LOAD_GLOBAL            BigWorld
    76 LOAD_ATTR              target
    79 CALL_FUNCTION          0
    82 LOAD_CONST             None
    85 COMPARE_OP             8
    88 POP_JUMP_IF_TRUE       to 131
    91 LOAD_GLOBAL            isinstance
    94 LOAD_GLOBAL            BigWorld
    97 LOAD_ATTR              target
   100 CALL_FUNCTION          0
   103 LOAD_DEREF             Vehicle
   106 CALL_FUNCTION          2
   109 POP_JUMP_IF_FALSE      to 613
   112 LOAD_GLOBAL            BigWorld
   115 LOAD_ATTR              target
   118 CALL_FUNCTION          0
   121 LOAD_ATTR              isAlive
   124 CALL_FUNCTION          0
   127 UNARY_NOT
   128 POP_JUMP_IF_FALSE      to 613
   131 LOAD_CONST             0
   134 STORE_FAST             fam
   137 SETUP_LOOP             to 613
   140 LOAD_GLOBAL            BigWorld
   143 LOAD_ATTR              entities
   146 LOAD_ATTR              values
   149 CALL_FUNCTION          0
   152 GET_ITER
   153 FOR_ITER               to 612
   156 STORE_FAST             vehicle
   159 LOAD_GLOBAL            isinstance
   162 LOAD_FAST              vehicle
   165 LOAD_DEREF             Vehicle
   168 CALL_FUNCTION          2
   171 POP_JUMP_IF_FALSE      to 153
   174 LOAD_FAST              vehicle
   177 LOAD_ATTR              isStarted
   180 POP_JUMP_IF_FALSE      to 153
   183 LOAD_CONST             None
   186 STORE_FAST             adgclr
   189 LOAD_GLOBAL            getattr
   192 LOAD_FAST              vehicle
   195 LOAD_CONST             'zj_adgclr'
   198 LOAD_CONST             None
   201 CALL_FUNCTION          3
   204 STORE_FAST             t_clr
   207 LOAD_DEREF             mody
   210 LOAD_ATTR              freeAttackMarker
   213 POP_JUMP_IF_FALSE      to 319
   216 LOAD_FAST              vehicle
   219 LOAD_ATTR              publicInfo
   222 LOAD_CONST             'team'
   225 BINARY_SUBSCR
   226 LOAD_GLOBAL            BigWorld
   229 LOAD_ATTR              player
   232 CALL_FUNCTION          0
   235 LOAD_ATTR              team
   238 COMPARE_OP             3
   241 POP_JUMP_IF_FALSE      to 319
   244 LOAD_DEREF             GetObstacle
   247 LOAD_FAST              vehicle
   250 LOAD_CONST             'gun'
   253 LOAD_DEREF             mody
   256 LOAD_ATTR              freeAttackMarker
   259 CALL_FUNCTION          3
   262 UNARY_NOT
   263 POP_JUMP_IF_FALSE      to 319
   266 LOAD_DEREF             GetVehicleViewAngle
   269 LOAD_FAST              vehicle
   272 LOAD_CONST             0.7
   275 CALL_FUNCTION          2
   278 POP_JUMP_IF_FALSE      to 319
   281 LOAD_CONST             3
   284 DUP_TOP
   285 STORE_FAST             adgclr
   288 LOAD_FAST              vehicle
   291 STORE_ATTR             zj_adgclr
   294 LOAD_FAST              t_clr
   297 LOAD_FAST              adgclr
   300 COMPARE_OP             3
   303 POP_JUMP_IF_FALSE      to 153
   306 LOAD_DEREF             addEdge
   309 LOAD_FAST              vehicle
   312 CALL_FUNCTION          1
   315 POP_TOP
   316 JUMP_ABSOLUTE          to 153
   319 LOAD_FAST              fam
   322 LOAD_CONST             3
   325 COMPARE_OP             2
   328 POP_JUMP_IF_FALSE      to 344
   331 LOAD_DEREF             removeEdge
   334 LOAD_FAST              vehicle
   337 CALL_FUNCTION          1
   340 POP_TOP
   341 JUMP_ABSOLUTE          to 153
   344 LOAD_GLOBAL            BigWorld
   347 LOAD_ATTR              player
   350 CALL_FUNCTION          0
   353 LOAD_ATTR              getOwnVehiclePosition
   356 CALL_FUNCTION          0
   359 LOAD_FAST              vehicle
   362 LOAD_ATTR              position
   365 BINARY_SUBTRACT
   366 LOAD_ATTR              length
   369 STORE_FAST             distance
   372 LOAD_FAST              vehicle
   375 LOAD_ATTR              isAlive
   378 CALL_FUNCTION          0
   381 POP_JUMP_IF_FALSE      to 594
   384 LOAD_FAST              vehicle
   387 LOAD_ATTR              publicInfo
   390 LOAD_CONST             'team'
   393 BINARY_SUBSCR
   394 LOAD_GLOBAL            BigWorld
   397 LOAD_ATTR              player
   400 CALL_FUNCTION          0
   403 LOAD_ATTR              team
   406 COMPARE_OP             3
   409 POP_JUMP_IF_FALSE      to 594
   412 LOAD_FAST              vehicle
   415 LOAD_ATTR              isPlayerVehicle
   418 UNARY_NOT
   419 POP_JUMP_IF_FALSE      to 594
   422 LOAD_DEREF             mody
   425 LOAD_ATTR              distanceClose
   428 LOAD_FAST              distance
   431 DUP_TOP
   432 ROT_THREE
   433 COMPARE_OP             0
   436 JUMP_IF_FALSE_OR_POP   to 607
   439 LOAD_DEREF             mody
   442 LOAD_ATTR              distanceFar
   445 COMPARE_OP             0
   448 POP_JUMP_IF_FALSE      to 530
   451 LOAD_DEREF             GetObstacle
   454 LOAD_FAST              vehicle
   457 LOAD_CONST             'camera'
   460 LOAD_DEREF             mody
   463 LOAD_ATTR              forObstacleOnlyEnemies
   466 CALL_FUNCTION          3
   469 POP_JUMP_IF_FALSE      to 530
   472 LOAD_DEREF             GetVehicleViewAngle
   475 LOAD_FAST              vehicle
   478 LOAD_DEREF             mody
   481 LOAD_ATTR              viewAngle
   484 LOAD_DEREF             mody
   487 LOAD_ATTR              viewAngleEnable
   490 CALL_FUNCTION          3
   493 POP_JUMP_IF_FALSE      to 530
   496 LOAD_GLOBAL            BigWorld
   499 LOAD_ATTR              player
   502 CALL_FUNCTION          0
   505 LOAD_ATTR              inputHandler
   508 LOAD_ATTR              ctrlModeName
   511 LOAD_CONST             ('sniper', 'dualgun', 'twinGun')
   514 COMPARE_OP             7
   517 JUMP_IF_FALSE_OR_POP   to 526
   520 LOAD_DEREF             mody
   523 LOAD_ATTR              sniperOnly
   526 UNARY_NOT
   527 POP_JUMP_IF_TRUE       to 539
   530 LOAD_DEREF             mody
   533 LOAD_ATTR              altFlag
   536 POP_JUMP_IF_FALSE      to 594
   539 LOAD_CONST             0
   542 LOAD_FAST              vehicle
   545 STORE_ATTR             zj_adgclr
   548 LOAD_FAST              adgclr
   551 LOAD_CONST             3
   554 COMPARE_OP             3
   557 POP_JUMP_IF_FALSE      to 569
   560 LOAD_FAST              vehicle
   563 LOAD_ATTR              zj_adgclr
   566 STORE_FAST             adgclr
   569 LOAD_FAST              t_clr
   572 LOAD_FAST              adgclr
   575 COMPARE_OP             3
   578 POP_JUMP_IF_FALSE      to 153
   581 LOAD_DEREF             addEdge
   584 LOAD_FAST              vehicle
   587 CALL_FUNCTION          1
   590 POP_TOP
   591 JUMP_ABSOLUTE          to 153
   594 LOAD_DEREF             removeEdge
   597 LOAD_FAST              vehicle
   600 CALL_FUNCTION          1
   603 POP_TOP
   604 JUMP_ABSOLUTE          to 153
   607 ROT_TWO
   608 POP_TOP
   609 JUMP_ABSOLUTE          to 448
   612 POP_BLOCK
   613 LOAD_DEREF             mody
   616 LOAD_ATTR              batleStart
   619 POP_JUMP_IF_FALSE      to 650
   622 LOAD_DEREF             mody
   625 LOAD_ATTR              modEnable
   628 POP_JUMP_IF_FALSE      to 650
   631 LOAD_GLOBAL            BigWorld
   634 LOAD_ATTR              callback
   637 LOAD_DEREF             mody
   640 LOAD_ATTR              tick
   643 LOAD_DEREF             DrawControl
   646 CALL_FUNCTION          2
   649 POP_TOP
   650 LOAD_CONST             None
   653 RETURN_VALUE

  # onVehicleKilled(argc=1) varnames=('targetID', 'args', 'vehicle')
     0 LOAD_GLOBAL            BigWorld
     3 LOAD_ATTR              entity
     6 LOAD_FAST              targetID
     9 CALL_FUNCTION          1
    12 STORE_FAST             vehicle
    15 LOAD_DEREF             removeEdge
    18 LOAD_FAST              vehicle
    21 CALL_FUNCTION          1
    24 POP_TOP
    25 LOAD_CONST             None
    28 RETURN_VALUE

  # new_startVisual(argc=2) varnames=('self', 'old_func')
     0 LOAD_FAST              old_func
     3 LOAD_FAST              self
     6 CALL_FUNCTION          1
     9 POP_TOP
    10 LOAD_CONST             None
    13 RETURN_VALUE

  # new_stopVisual(argc=3) varnames=('self', 'vehicle', 'old_func')
     0 LOAD_DEREF             removeEdge
     3 LOAD_FAST              vehicle
     6 CALL_FUNCTION          1
     9 POP_TOP
    10 LOAD_FAST              old_func
    13 LOAD_FAST              self
    16 LOAD_FAST              vehicle
    19 CALL_FUNCTION          2
    22 POP_TOP
    23 LOAD_CONST             None
    26 RETURN_VALUE

  # new_targetFocus(argc=3) varnames=('self', 'entity', 'old_targetFocus', 'vehicle')
     0 LOAD_DEREF             mody
     3 LOAD_ATTR              modEnable
     6 POP_JUMP_IF_FALSE      to 114
     9 LOAD_GLOBAL            isinstance
    12 LOAD_FAST              entity
    15 LOAD_DEREF             Vehicle
    18 CALL_FUNCTION          2
    21 POP_JUMP_IF_FALSE      to 114
    24 LOAD_FAST              entity
    27 LOAD_ATTR              isAlive
    30 CALL_FUNCTION          0
    33 POP_JUMP_IF_FALSE      to 114
    36 SETUP_LOOP             to 114
    39 LOAD_GLOBAL            BigWorld
    42 LOAD_ATTR              entities
    45 LOAD_ATTR              values
    48 CALL_FUNCTION          0
    51 GET_ITER
    52 FOR_ITER               to 113
    55 STORE_FAST             vehicle
    58 LOAD_GLOBAL            isinstance
    61 LOAD_FAST              vehicle
    64 LOAD_DEREF             Vehicle
    67 CALL_FUNCTION          2
    70 POP_JUMP_IF_FALSE      to 52
    73 LOAD_GLOBAL            BigWorld
    76 LOAD_ATTR              target
    79 CALL_FUNCTION          0
    82 LOAD_FAST              vehicle
    85 COMPARE_OP             2
    88 POP_JUMP_IF_FALSE      to 100
    91 LOAD_CONST             None
    94 LOAD_FAST              vehicle
    97 STORE_ATTR             zj_adgclr
   100 LOAD_DEREF             removeEdge
   103 LOAD_FAST              vehicle
   106 CALL_FUNCTION          1
   109 POP_TOP
   110 JUMP_ABSOLUTE          to 52
   113 POP_BLOCK
   114 LOAD_FAST              old_targetFocus
   117 LOAD_FAST              self
   120 LOAD_FAST              entity
   123 CALL_FUNCTION          2
   126 POP_TOP
   127 LOAD_CONST             None
   130 RETURN_VALUE

  # new_targetBlur(argc=3) varnames=('self', 'prevEntity', 'old_targetBlur', 'vehicle')
     0 LOAD_FAST              old_targetBlur
     3 LOAD_FAST              self
     6 LOAD_FAST              prevEntity
     9 CALL_FUNCTION          2
    12 POP_TOP
    13 LOAD_DEREF             mody
    16 LOAD_ATTR              modEnable
    19 POP_JUMP_IF_FALSE      to 63
    22 SETUP_LOOP             to 63
    25 LOAD_GLOBAL            BigWorld
    28 LOAD_ATTR              entities
    31 LOAD_ATTR              values
    34 CALL_FUNCTION          0
    37 GET_ITER
    38 FOR_ITER               to 62
    41 STORE_FAST             vehicle
    44 LOAD_GLOBAL            isinstance
    47 LOAD_FAST              vehicle
    50 LOAD_DEREF             Vehicle
    53 CALL_FUNCTION          2
    56 POP_JUMP_IF_FALSE      to 38
    59 JUMP_ABSOLUTE          to 38
    62 POP_BLOCK
    63 LOAD_CONST             None
    66 RETURN_VALUE

  # new_doHighlightOperation(argc=3) varnames=('self', 'status', 'args', 'vehicle', 'adgclr')
     0 LOAD_DEREF             mody
     3 LOAD_ATTR              modEnable
     6 UNARY_NOT
     7 POP_JUMP_IF_TRUE       to 40
    10 LOAD_GLOBAL            BigWorld
    13 LOAD_ATTR              target
    16 CALL_FUNCTION          0
    19 POP_JUMP_IF_FALSE      to 60
    22 LOAD_GLOBAL            BigWorld
    25 LOAD_ATTR              target
    28 CALL_FUNCTION          0
    31 LOAD_ATTR              isAlive
    34 CALL_FUNCTION          0
    37 POP_JUMP_IF_FALSE      to 60
    40 LOAD_DEREF             old_doHighlightOperation
    43 LOAD_FAST              self
    46 LOAD_FAST              status
    49 LOAD_FAST              args
    52 CALL_FUNCTION          3
    55 POP_TOP
    56 LOAD_CONST             None
    59 RETURN_VALUE
    60 LOAD_FAST              self
    63 LOAD_ATTR              _Highlighter__vehicle
    66 STORE_FAST             vehicle
    69 LOAD_FAST              status
    72 LOAD_FAST              self
    75 LOAD_ATTR              HIGHLIGHT_ON
    78 BINARY_AND
    79 POP_JUMP_IF_FALSE      to 172
    82 LOAD_GLOBAL            getattr
    85 LOAD_FAST              vehicle
    88 LOAD_CONST             'zj_adgclr'
    91 LOAD_CONST             None
    94 CALL_FUNCTION          3
    97 STORE_FAST             adgclr
   100 LOAD_FAST              adgclr
   103 LOAD_CONST             None
   106 COMPARE_OP             9
   109 POP_JUMP_IF_FALSE      to 130
   112 LOAD_FAST              adgclr
   115 LOAD_GLOBAL            False
   118 LOAD_CONST             0
   121 LOAD_GLOBAL            False
   124 BUILD_TUPLE            4
   127 STORE_FAST             args
   130 LOAD_GLOBAL            BigWorld
   133 LOAD_ATTR              addEdgeDetectEntity
   136 LOAD_FAST              vehicle
   139 LOAD_FAST              self
   142 LOAD_ATTR              _Highlighter__collisions
   145 LOAD_FAST              args
   148 CALL_FUNCTION_VAR      2
   151 POP_TOP
   152 LOAD_FAST              self
   155 LOAD_ATTR              _Highlighter__updateHighlightComponent
   158 LOAD_FAST              status
   161 LOAD_FAST              args
   164 CALL_FUNCTION          2
   167 POP_TOP
   168 LOAD_CONST             None
   171 RETURN_VALUE
   172 LOAD_GLOBAL            BigWorld
   175 LOAD_ATTR              delEdgeDetectEntity
   178 LOAD_FAST              vehicle
   181 CALL_FUNCTION          1
   184 POP_TOP
   185 JUMP_ABSOLUTE          to 152

  # new_doHighlightOperation(argc=4) varnames=('self', 'vehicle', 'status', 'args', 'adgclr')
     0 LOAD_DEREF             mody
     3 LOAD_ATTR              modEnable
     6 UNARY_NOT
     7 POP_JUMP_IF_TRUE       to 40
    10 LOAD_GLOBAL            BigWorld
    13 LOAD_ATTR              target
    16 CALL_FUNCTION          0
    19 POP_JUMP_IF_FALSE      to 63
    22 LOAD_GLOBAL            BigWorld
    25 LOAD_ATTR              target
    28 CALL_FUNCTION          0
    31 LOAD_ATTR              isAlive
    34 CALL_FUNCTION          0
    37 POP_JUMP_IF_FALSE      to 63
    40 LOAD_DEREF             old_doHighlightOperation
    43 LOAD_FAST              self
    46 LOAD_FAST              vehicle
    49 LOAD_FAST              status
    52 LOAD_FAST              args
    55 CALL_FUNCTION          4
    58 POP_TOP
    59 LOAD_CONST             None
    62 RETURN_VALUE
    63 LOAD_FAST              status
    66 LOAD_FAST              self
    69 LOAD_ATTR              HIGHLIGHT_ON
    72 BINARY_AND
    73 POP_JUMP_IF_FALSE      to 89
    76 LOAD_GLOBAL            BigWorld
    79 LOAD_ATTR              wgDelEdgeDetectEntity
    82 LOAD_FAST              vehicle
    85 CALL_FUNCTION          1
    88 POP_TOP
    89 LOAD_GLOBAL            getattr
    92 LOAD_FAST              vehicle
    95 LOAD_CONST             'zj_adgclr'
    98 LOAD_CONST             None
   101 CALL_FUNCTION          3
   104 STORE_FAST             adgclr
   107 LOAD_FAST              adgclr
   110 LOAD_CONST             None
   113 COMPARE_OP             9
   116 POP_JUMP_IF_FALSE      to 137
   119 LOAD_FAST              adgclr
   122 LOAD_GLOBAL            False
   125 LOAD_CONST             0
   128 LOAD_GLOBAL            False
   131 BUILD_TUPLE            4
   134 STORE_FAST             args
   137 LOAD_FAST              self
   140 LOAD_ATTR              _Highlighter__updateHighlightComponent
   143 LOAD_FAST              vehicle
   146 LOAD_FAST              status
   149 LOAD_FAST              args
   152 CALL_FUNCTION          3
   155 POP_TOP
   156 LOAD_CONST             None
   159 RETURN_VALUE

  # GetVehicleViewAngle(argc=3) varnames=('vehicle', 'viewAngle', 'enable', 'player', 'dir', 'start', 'vehiclePos', 'vehicleDesc', 'toVehicleDist', 'camVehiclePos', 'camVehicleDst', 'sizeXRay', 'minToVehicleDist', 'scanXRay')
     0 LOAD_FAST              enable
     3 POP_JUMP_IF_TRUE       to 10
     6 LOAD_GLOBAL            True
     9 RETURN_VALUE
    10 SETUP_EXCEPT           to 291
    13 LOAD_GLOBAL            BigWorld
    16 LOAD_ATTR              player
    19 CALL_FUNCTION          0
    22 STORE_FAST             player
    25 LOAD_DEREF             cameras
    28 LOAD_ATTR              getWorldRayAndPoint
    31 LOAD_GLOBAL            BigWorld
    34 LOAD_ATTR              player
    37 CALL_FUNCTION          0
    40 LOAD_ATTR              guiSessionProvider
    43 LOAD_ATTR              shared
    46 LOAD_ATTR              crosshair
    49 LOAD_ATTR              getOffset
    52 CALL_FUNCTION          0
    55 CALL_FUNCTION_VAR      0
    58 UNPACK_SEQUENCE        2
    61 STORE_FAST             dir
    64 STORE_FAST             start
    67 LOAD_FAST              dir
    70 LOAD_ATTR              normalise
    73 CALL_FUNCTION          0
    76 POP_TOP
    77 LOAD_FAST              vehicle
    80 LOAD_ATTR              isAlive
    83 CALL_FUNCTION          0
    86 POP_JUMP_IF_FALSE      to 274
    89 LOAD_FAST              vehicle
    92 LOAD_ATTR              position
    95 LOAD_CONST             1
    98 BINARY_MULTIPLY
    99 STORE_FAST             vehiclePos
   102 LOAD_FAST              vehicle
   105 LOAD_ATTR              typeDescriptor
   108 STORE_FAST             vehicleDesc
   111 LOAD_FAST              vehiclePos
   114 DUP_TOP
   115 LOAD_ATTR              y
   118 LOAD_FAST              vehicleDesc
   121 LOAD_ATTR              chassis
   124 LOAD_ATTR              hullPosition
   127 LOAD_ATTR              y
   130 LOAD_FAST              vehicleDesc
   133 LOAD_ATTR              hull
   136 LOAD_ATTR              turretPositions
   139 LOAD_CONST             0
   142 BINARY_SUBSCR
   143 LOAD_ATTR              y
   146 LOAD_CONST             0.5
   149 BINARY_MULTIPLY
   150 BINARY_ADD
   151 INPLACE_ADD
   152 ROT_TWO
   153 STORE_ATTR             y
   156 LOAD_FAST              start
   159 LOAD_FAST              vehiclePos
   162 BINARY_SUBTRACT
   163 LOAD_ATTR              length
   166 STORE_FAST             toVehicleDist
   169 LOAD_FAST              start
   172 LOAD_FAST              dir
   175 LOAD_FAST              toVehicleDist
   178 BINARY_MULTIPLY
   179 BINARY_ADD
   180 STORE_FAST             camVehiclePos
   183 LOAD_FAST              camVehiclePos
   186 LOAD_FAST              vehiclePos
   189 BINARY_SUBTRACT
   190 LOAD_ATTR              length
   193 STORE_FAST             camVehicleDst
   196 LOAD_CONST             4.0
   199 STORE_FAST             sizeXRay
   202 LOAD_CONST             50
   205 STORE_FAST             minToVehicleDist
   208 LOAD_FAST              toVehicleDist
   211 LOAD_FAST              minToVehicleDist
   214 COMPARE_OP             1
   217 POP_JUMP_IF_FALSE      to 278
   220 LOAD_GLOBAL            mode
   223 LOAD_CONST             'gun'
   226 COMPARE_OP             2
   229 POP_JUMP_IF_FALSE      to 278
   232 LOAD_FAST              sizeXRay
   235 LOAD_CONST             1
   238 LOAD_CONST             1
   241 LOAD_FAST              toVehicleDist
   244 LOAD_FAST              minToVehicleDist
   247 BINARY_DIVIDE
   248 BINARY_SUBTRACT
   249 BINARY_ADD
   250 BINARY_MULTIPLY
   251 LOAD_CONST             1.5
   254 BINARY_MULTIPLY
   255 STORE_FAST             scanXRay
   258 LOAD_FAST              scanXRay
   261 LOAD_FAST              camVehicleDst
   264 COMPARE_OP             4
   267 POP_JUMP_IF_FALSE      to 274
   270 LOAD_GLOBAL            True
   273 RETURN_VALUE
   274 LOAD_GLOBAL            False
   277 RETURN_VALUE
   278 LOAD_FAST              toVehicleDist
   281 LOAD_FAST              viewAngle
   284 BINARY_MULTIPLY
   285 STORE_FAST             scanXRay
   288 JUMP_ABSOLUTE          to 258
   291 POP_TOP
   292 POP_TOP
   293 POP_TOP
   294 LOAD_GLOBAL            True
   297 RETURN_VALUE

  # GetObstacle(argc=3) varnames=('vehicle', 'mode', 'enable', 'ownVehicle', 'start', 'end', 'testRes', 'collData')
     0 LOAD_FAST              enable
     3 POP_JUMP_IF_FALSE      to 175
     6 SETUP_EXCEPT           to 219
     9 LOAD_GLOBAL            BigWorld
    12 LOAD_ATTR              player
    15 CALL_FUNCTION          0
    18 LOAD_ATTR              getVehicleAttached
    21 CALL_FUNCTION          0
    24 STORE_FAST             ownVehicle
    27 LOAD_FAST              mode
    30 LOAD_CONST             'camera'
    33 COMPARE_OP             2
    36 POP_JUMP_IF_FALSE      to 183
    39 LOAD_GLOBAL            BigWorld
    42 LOAD_ATTR              camera
    45 CALL_FUNCTION          0
    48 LOAD_ATTR              position
    51 STORE_FAST             start
    54 LOAD_FAST              start
    57 LOAD_CONST             None
    60 COMPARE_OP             8
    63 POP_JUMP_IF_FALSE      to 70
    66 LOAD_GLOBAL            True
    69 RETURN_VALUE
    70 LOAD_FAST              vehicle
    73 LOAD_ATTR              model
    76 LOAD_ATTR              node
    79 LOAD_CONST             'gun'
    82 CALL_FUNCTION          1
    85 LOAD_ATTR              position
    88 STORE_FAST             end
    91 LOAD_DEREF             collideDynamicAndStatic
    94 LOAD_FAST              start
    97 LOAD_FAST              end
   100 LOAD_FAST              ownVehicle
   103 LOAD_ATTR              id
   106 BUILD_TUPLE            1
   109 LOAD_CONST             128
   112 LOAD_GLOBAL            True
   115 CALL_FUNCTION          5
   118 STORE_FAST             testRes
   121 LOAD_FAST              testRes
   124 LOAD_CONST             None
   127 COMPARE_OP             9
   130 POP_JUMP_IF_FALSE      to 179
   133 LOAD_FAST              testRes
   136 LOAD_CONST             1
   139 BINARY_SUBSCR
   140 STORE_FAST             collData
   143 LOAD_FAST              collData
   146 LOAD_CONST             None
   149 COMPARE_OP             9
   152 POP_JUMP_IF_FALSE      to 174
   155 LOAD_FAST              collData
   158 LOAD_ATTR              entity
   161 LOAD_FAST              vehicle
   164 COMPARE_OP             2
   167 POP_JUMP_IF_FALSE      to 174
   170 LOAD_GLOBAL            False
   173 RETURN_VALUE
   174 POP_BLOCK
   175 LOAD_GLOBAL            True
   178 RETURN_VALUE
   179 LOAD_GLOBAL            False
   182 RETURN_VALUE
   183 LOAD_FAST              mode
   186 LOAD_CONST             'gun'
   189 COMPARE_OP             2
   192 POP_JUMP_IF_FALSE      to 70
   195 LOAD_FAST              ownVehicle
   198 LOAD_ATTR              model
   201 LOAD_ATTR              node
   204 LOAD_CONST             'gun'
   207 CALL_FUNCTION          1
   210 LOAD_ATTR              position
   213 STORE_FAST             start
   216 JUMP_ABSOLUTE          to 70
   219 POP_TOP
   220 POP_TOP
   221 POP_TOP
   222 JUMP_ABSOLUTE          to 175

  # getBattleOn(argc=0) varnames=()
     0 LOAD_GLOBAL            hasattr
     3 LOAD_GLOBAL            BigWorld
     6 LOAD_ATTR              player
     9 CALL_FUNCTION          0
    12 LOAD_CONST             'arena'
    15 CALL_FUNCTION          2
    18 RETURN_VALUE

  # getIsSquad(argc=1) varnames=('id',)
     0 LOAD_DEREF             getBattleOn
     3 CALL_FUNCTION          0
     6 JUMP_IF_FALSE_OR_POP   to 36
     9 LOAD_GLOBAL            BigWorld
    12 LOAD_ATTR              player
    15 CALL_FUNCTION          0
    18 LOAD_ATTR              guiSessionProvider
    21 LOAD_ATTR              getCtx
    24 CALL_FUNCTION          0
    27 LOAD_ATTR              isSquadMan
    30 LOAD_FAST              id
    33 CALL_FUNCTION          1
    36 RETURN_VALUE

  # getIsPlayer(argc=1) varnames=('id',)
     0 LOAD_DEREF             getBattleOn
     3 CALL_FUNCTION          0
     6 JUMP_IF_FALSE_OR_POP   to 27
     9 LOAD_GLOBAL            BigWorld
    12 LOAD_ATTR              player
    15 CALL_FUNCTION          0
    18 LOAD_ATTR              playerVehicleID
    21 LOAD_FAST              id
    24 COMPARE_OP             2
    27 RETURN_VALUE

  # getIsLive(argc=1) varnames=('id',)
     0 SETUP_EXCEPT           to 41
     3 LOAD_DEREF             getBattleOn
     6 CALL_FUNCTION          0
     9 JUMP_IF_FALSE_OR_POP   to 40
    12 LOAD_GLOBAL            BigWorld
    15 LOAD_ATTR              player
    18 CALL_FUNCTION          0
    21 LOAD_ATTR              arena
    24 LOAD_ATTR              vehicles
    27 LOAD_ATTR              get
    30 LOAD_FAST              id
    33 CALL_FUNCTION          1
    36 LOAD_CONST             'isAlive'
    39 BINARY_SUBSCR
    40 RETURN_VALUE
    41 POP_TOP
    42 POP_TOP
    43 POP_TOP
    44 LOAD_CONST             None
    47 RETURN_VALUE

  # getIsFriendly(argc=1) varnames=('id',)
     0 LOAD_DEREF             getBattleOn
     3 CALL_FUNCTION          0
     6 JUMP_IF_FALSE_OR_POP   to 67
     9 LOAD_GLOBAL            BigWorld
    12 LOAD_ATTR              player
    15 CALL_FUNCTION          0
    18 LOAD_ATTR              arena
    21 LOAD_ATTR              vehicles
    24 LOAD_GLOBAL            BigWorld
    27 LOAD_ATTR              player
    30 CALL_FUNCTION          0
    33 LOAD_ATTR              playerVehicleID
    36 BINARY_SUBSCR
    37 LOAD_CONST             'team'
    40 BINARY_SUBSCR
    41 LOAD_GLOBAL            BigWorld
    44 LOAD_ATTR              player
    47 CALL_FUNCTION          0
    50 LOAD_ATTR              arena
    53 LOAD_ATTR              vehicles
    56 LOAD_FAST              id
    59 BINARY_SUBSCR
    60 LOAD_CONST             'team'
    63 BINARY_SUBSCR
    64 COMPARE_OP             2
    67 RETURN_VALUE

  # getIsVisible(argc=1) varnames=('id', 'vehicle')
     0 LOAD_DEREF             getBattleOn
     3 CALL_FUNCTION          0
     6 POP_JUMP_IF_FALSE      to 43
     9 LOAD_GLOBAL            BigWorld
    12 LOAD_ATTR              entity
    15 LOAD_FAST              id
    18 CALL_FUNCTION          1
    21 STORE_FAST             vehicle
    24 LOAD_FAST              vehicle
    27 LOAD_CONST             None
    30 COMPARE_OP             9
    33 JUMP_IF_FALSE_OR_POP   to 42
    36 LOAD_FAST              vehicle
    39 LOAD_ATTR              isStarted
    42 RETURN_VALUE
    43 LOAD_CONST             None
    46 RETURN_VALUE

  # getIsVisibleLiveEnemy(argc=1) varnames=('id',)
     0 LOAD_DEREF             getIsVisible
     3 LOAD_FAST              id
     6 CALL_FUNCTION          1
     9 JUMP_IF_FALSE_OR_POP   to 34
    12 LOAD_DEREF             getIsLive
    15 LOAD_FAST              id
    18 CALL_FUNCTION          1
    21 JUMP_IF_FALSE_OR_POP   to 34
    24 LOAD_DEREF             getIsVisible
    27 LOAD_FAST              id
    30 CALL_FUNCTION          1
    33 UNARY_NOT
    34 RETURN_VALUE

  # LoadConfLoop(argc=0) varnames=('file_xml', 'tick', 'file_time')
     0 LOAD_DEREF             mody
     3 LOAD_ATTR              PATH_MODS
     6 LOAD_DEREF             mody
     9 LOAD_ATTR              FILE_xml
    12 BINARY_ADD
    13 STORE_FAST             file_xml
    16 LOAD_CONST             2
    19 STORE_FAST             tick
    22 SETUP_EXCEPT           to 145
    25 LOAD_GLOBAL            os
    28 LOAD_ATTR              path
    31 LOAD_ATTR              getmtime
    34 LOAD_FAST              file_xml
    37 CALL_FUNCTION          1
    40 STORE_FAST             file_time
    43 LOAD_GLOBAL            time
    46 LOAD_ATTR              time
    49 CALL_FUNCTION          0
    52 LOAD_FAST              file_time
    55 BINARY_SUBTRACT
    56 LOAD_FAST              tick
    59 LOAD_CONST             1.0
    62 BINARY_ADD
    63 COMPARE_OP             0
    66 POP_JUMP_IF_FALSE      to 115
    69 LOAD_DEREF             methodcaller
    72 LOAD_CONST             'as_showGreenMessageS'
    75 LOAD_CONST             ''
    78 LOAD_GLOBAL            APPLICATION
    81 LOAD_CONST             ' '
    84 BINARY_ADD
    85 LOAD_DEREF             mody
    88 LOAD_ATTR              TEXT_MESSAGE_ConfLoad
    91 BINARY_ADD
    92 CALL_FUNCTION          3
    95 LOAD_DEREF             PlayerAvatar
    98 LOAD_ATTR              selfMsg
   101 CALL_FUNCTION          1
   104 POP_TOP
   105 LOAD_DEREF             mody
   108 LOAD_ATTR              loadConf
   111 CALL_FUNCTION          0
   114 POP_TOP
   115 POP_BLOCK
   116 LOAD_DEREF             mody
   119 LOAD_ATTR              autoLoadConf
   122 POP_JUMP_IF_FALSE      to 141
   125 LOAD_GLOBAL            BigWorld
   128 LOAD_ATTR              callback
   131 LOAD_FAST              tick
   134 LOAD_DEREF             LoadConfLoop
   137 CALL_FUNCTION          2
   140 POP_TOP
   141 LOAD_CONST             None
   144 RETURN_VALUE
   145 POP_TOP
   146 POP_TOP
   147 POP_TOP
   148 JUMP_ABSOLUTE          to 116

  # new__startBattle(argc=1) varnames=('self',)
     0 LOAD_DEREF             old__startBattle
     3 LOAD_FAST              self
     6 CALL_FUNCTION          1
     9 POP_TOP
    10 LOAD_DEREF             mody
    13 LOAD_ATTR              GLOBAL_ENABLE
    16 JUMP_IF_FALSE_OR_POP   to 25
    19 LOAD_DEREF             getResolut
    22 CALL_FUNCTION          0
    25 LOAD_DEREF             mody
    28 STORE_ATTR             modEnable
    31 LOAD_DEREF             mody
    34 LOAD_ATTR              GLOBAL_ENABLE
    37 POP_JUMP_IF_FALSE      to 115
    40 LOAD_DEREF             getResolut
    43 CALL_FUNCTION          0
    46 POP_JUMP_IF_FALSE      to 115
    49 LOAD_GLOBAL            BigWorld
    52 LOAD_ATTR              player
    55 CALL_FUNCTION          0
    58 LOAD_ATTR              arena
    61 DUP_TOP
    62 LOAD_ATTR              onVehicleKilled
    65 LOAD_DEREF             onVehicleKilled
    68 INPLACE_ADD
    69 ROT_TWO
    70 STORE_ATTR             onVehicleKilled
    73 LOAD_DEREF             mody
    76 LOAD_ATTR              loadConf
    79 CALL_FUNCTION          0
    82 POP_TOP
    83 LOAD_DEREF             mody
    86 LOAD_ATTR              interactivSettings
    89 POP_JUMP_IF_FALSE      to 99
    92 LOAD_DEREF             LoadConfLoop
    95 CALL_FUNCTION          0
    98 POP_TOP
    99 LOAD_GLOBAL            True
   102 LOAD_DEREF             mody
   105 STORE_ATTR             batleStart
   108 LOAD_DEREF             DrawControl
   111 CALL_FUNCTION          0
   114 POP_TOP
   115 LOAD_CONST             None
   118 RETURN_VALUE

  # new__stopBattle(argc=1) varnames=('self',)
     0 LOAD_DEREF             old__stopBattle
     3 LOAD_FAST              self
     6 CALL_FUNCTION          1
     9 POP_TOP
    10 LOAD_GLOBAL            BigWorld
    13 LOAD_ATTR              player
    16 CALL_FUNCTION          0
    19 LOAD_ATTR              arena
    22 DUP_TOP
    23 LOAD_ATTR              onVehicleKilled
    26 LOAD_DEREF             onVehicleKilled
    29 INPLACE_SUBTRACT
    30 ROT_TWO
    31 STORE_ATTR             onVehicleKilled
    34 LOAD_GLOBAL            False
    37 LOAD_DEREF             mody
    40 STORE_ATTR             batleStart
    43 LOAD_DEREF             mody
    46 LOAD_ATTR              clearVars
    49 CALL_FUNCTION          0
    52 POP_TOP
    53 LOAD_CONST             None
    56 RETURN_VALUE

  # new_PlayerHandleKey_init(argc=4) varnames=('self', 'isDown', 'key', 'mods')
     0 LOAD_DEREF             mody
     3 LOAD_ATTR              GLOBAL_ENABLE
     6 POP_JUMP_IF_FALSE      to 357
     9 LOAD_DEREF             getResolut
    12 CALL_FUNCTION          0
    15 POP_JUMP_IF_FALSE      to 357
    18 LOAD_FAST              key
    21 LOAD_CONST             0
    24 COMPARE_OP             3
    27 POP_JUMP_IF_FALSE      to 357
    30 LOAD_DEREF             mody
    33 LOAD_ATTR              autoLoadConf
    36 UNARY_NOT
    37 POP_JUMP_IF_FALSE      to 156
    40 LOAD_FAST              key
    43 LOAD_GLOBAL            getattr
    46 LOAD_DEREF             Keys
    49 LOAD_DEREF             mody
    52 LOAD_ATTR              toggleKey
    55 LOAD_CONST             None
    58 CALL_FUNCTION          3
    61 COMPARE_OP             2
    64 POP_JUMP_IF_FALSE      to 156
    67 LOAD_FAST              isDown
    70 POP_JUMP_IF_FALSE      to 156
    73 LOAD_FAST              mods
    76 LOAD_CONST             2
    79 COMPARE_OP             2
    82 POP_JUMP_IF_FALSE      to 156
    85 LOAD_DEREF             mody
    88 LOAD_ATTR              interactivSettings
    91 POP_JUMP_IF_FALSE      to 156
    94 LOAD_DEREF             mody
    97 LOAD_ATTR              loadConf
   100 CALL_FUNCTION          0
   103 POP_TOP
   104 LOAD_DEREF             methodcaller
   107 LOAD_CONST             'as_showGreenMessageS'
   110 LOAD_CONST             ''
   113 LOAD_GLOBAL            APPLICATION
   116 LOAD_CONST             ' '
   119 BINARY_ADD
   120 LOAD_DEREF             mody
   123 LOAD_ATTR              TEXT_MESSAGE_ConfLoad
   126 BINARY_ADD
   127 CALL_FUNCTION          3
   130 LOAD_DEREF             PlayerAvatar
   133 LOAD_ATTR              selfMsg
   136 CALL_FUNCTION          1
   139 POP_TOP
   140 LOAD_DEREF             mody
   143 LOAD_ATTR              autoLoadConf
   146 POP_JUMP_IF_FALSE      to 156
   149 LOAD_DEREF             LoadConfLoop
   152 CALL_FUNCTION          0
   155 POP_TOP
   156 LOAD_FAST              key
   159 LOAD_GLOBAL            getattr
   162 LOAD_DEREF             Keys
   165 LOAD_DEREF             mody
   168 LOAD_ATTR              altKey
   171 LOAD_CONST             None
   174 CALL_FUNCTION          3
   177 COMPARE_OP             2
   180 POP_JUMP_IF_FALSE      to 198
   183 LOAD_FAST              isDown
   186 POP_JUMP_IF_FALSE      to 198
   189 LOAD_GLOBAL            True
   192 LOAD_DEREF             mody
   195 STORE_ATTR             altFlag
   198 LOAD_FAST              key
   201 LOAD_GLOBAL            getattr
   204 LOAD_DEREF             Keys
   207 LOAD_DEREF             mody
   210 LOAD_ATTR              altKey
   213 LOAD_CONST             None
   216 CALL_FUNCTION          3
   219 COMPARE_OP             2
   222 POP_JUMP_IF_FALSE      to 241
   225 LOAD_FAST              isDown
   228 UNARY_NOT
   229 POP_JUMP_IF_FALSE      to 241
   232 LOAD_GLOBAL            False
   235 LOAD_DEREF             mody
   238 STORE_ATTR             altFlag
   241 LOAD_FAST              key
   244 LOAD_GLOBAL            getattr
   247 LOAD_DEREF             Keys
   250 LOAD_DEREF             mody
   253 LOAD_ATTR              toggleKey
   256 LOAD_CONST             None
   259 CALL_FUNCTION          3
   262 COMPARE_OP             2
   265 POP_JUMP_IF_FALSE      to 357
   268 LOAD_FAST              isDown
   271 POP_JUMP_IF_FALSE      to 357
   274 LOAD_FAST              mods
   277 LOAD_CONST             2
   280 COMPARE_OP             3
   283 POP_JUMP_IF_FALSE      to 357
   286 LOAD_DEREF             mody
   289 LOAD_ATTR              modEnable
   292 POP_JUMP_IF_TRUE       to 376
   295 LOAD_GLOBAL            True
   298 LOAD_DEREF             mody
   301 STORE_ATTR             modEnable
   304 LOAD_DEREF             methodcaller
   307 LOAD_CONST             'as_showGoldMessageS'
   310 LOAD_CONST             ''
   313 LOAD_GLOBAL            APPLICATION
   316 LOAD_CONST             ' '
   319 BINARY_ADD
   320 LOAD_DEREF             mody
   323 LOAD_ATTR              TEXT_MESSAGE_On
   326 BINARY_ADD
   327 CALL_FUNCTION          3
   330 LOAD_DEREF             PlayerAvatar
   333 LOAD_ATTR              selfMsg
   336 CALL_FUNCTION          1
   339 POP_TOP
   340 LOAD_DEREF             mody
   343 LOAD_ATTR              SwitchEdgeColor
   346 CALL_FUNCTION          0
   349 POP_TOP
   350 LOAD_DEREF             DrawControl
   353 CALL_FUNCTION          0
   356 POP_TOP
   357 LOAD_DEREF             pre_PlayerHandleKey_init
   360 LOAD_FAST              self
   363 LOAD_FAST              isDown
   366 LOAD_FAST              key
   369 LOAD_FAST              mods
   372 CALL_FUNCTION          4
   375 RETURN_VALUE
   376 LOAD_DEREF             mody
   379 LOAD_ATTR              sniperOnly
   382 POP_JUMP_IF_TRUE       to 433
   385 LOAD_GLOBAL            True
   388 LOAD_DEREF             mody
   391 STORE_ATTR             sniperOnly
   394 LOAD_DEREF             methodcaller
   397 LOAD_CONST             'as_showGoldMessageS'
   400 LOAD_CONST             ''
   403 LOAD_GLOBAL            APPLICATION
   406 LOAD_CONST             ' '
   409 BINARY_ADD
   410 LOAD_DEREF             mody
   413 LOAD_ATTR              TEXT_MESSAGE_OnSniper
   416 BINARY_ADD
   417 CALL_FUNCTION          3
   420 LOAD_DEREF             PlayerAvatar
   423 LOAD_ATTR              selfMsg
   426 CALL_FUNCTION          1
   429 POP_TOP
   430 JUMP_ABSOLUTE          to 357
   433 LOAD_GLOBAL            False
   436 LOAD_DEREF             mody
   439 STORE_ATTR             sniperOnly
   442 LOAD_GLOBAL            False
   445 LOAD_DEREF             mody
   448 STORE_ATTR             modEnable
   451 LOAD_DEREF             methodcaller
   454 LOAD_CONST             'as_showRedMessageS'
   457 LOAD_CONST             ''
   460 LOAD_GLOBAL            APPLICATION
   463 LOAD_CONST             ' '
   466 BINARY_ADD
   467 LOAD_DEREF             mody
   470 LOAD_ATTR              TEXT_MESSAGE_Off
   473 BINARY_ADD
   474 CALL_FUNCTION          3
   477 LOAD_DEREF             PlayerAvatar
   480 LOAD_ATTR              selfMsg
   483 CALL_FUNCTION          1
   486 POP_TOP
   487 LOAD_DEREF             mody
   490 LOAD_ATTR              SwitchEdgeColor
   493 CALL_FUNCTION          0
   496 POP_TOP
   497 JUMP_ABSOLUTE          to 357
